dynamic_form/__init__.py
dynamic_form/apps.py
dynamic_form/exceptions.py
dynamic_form/settings.py
dynamic_form/types.py
dynamic_form/urls.py
dynamic_form/views.py
dynamic_form/forms/__init__.py
dynamic_form/forms/dynamic_form.py
dynamic_form/static/dynamic_form/js/dynamic-form.js
dynamic_form/templates/dynamic_form/default_form.html
django_dynamic_form-0.1.dist-info/LICENSE
django_dynamic_form-0.1.dist-info/METADATA
django_dynamic_form-0.1.dist-info/WHEEL
django_dynamic_form-0.1.dist-info/top_level.txt
django_dynamic_form-0.1.dist-info/RECORD
